LICENSE
README.md
setup.py
NlpToolkit_PosTagger_Cy.egg-info/PKG-INFO
NlpToolkit_PosTagger_Cy.egg-info/SOURCES.txt
NlpToolkit_PosTagger_Cy.egg-info/dependency_links.txt
NlpToolkit_PosTagger_Cy.egg-info/requires.txt
NlpToolkit_PosTagger_Cy.egg-info/top_level.txt
PosTagger/DummyPosTagger.c
PosTagger/DummyPosTagger.pyx
PosTagger/HmmPosTagger.c
PosTagger/HmmPosTagger.pyx
PosTagger/NaivePosTagger.c
PosTagger/NaivePosTagger.pyx
PosTagger/PosTaggedCorpus.c
PosTagger/PosTaggedCorpus.pxd
PosTagger/PosTaggedCorpus.pyx
PosTagger/PosTaggedWord.c
PosTagger/PosTaggedWord.pxd
PosTagger/PosTaggedWord.pyx
PosTagger/PosTagger.c
PosTagger/PosTagger.pxd
PosTagger/PosTagger.pyx
PosTagger/__init__.py
nlptoolkit_postagger_cy.egg-info/PKG-INFO
nlptoolkit_postagger_cy.egg-info/SOURCES.txt
nlptoolkit_postagger_cy.egg-info/dependency_links.txt
nlptoolkit_postagger_cy.egg-info/requires.txt
nlptoolkit_postagger_cy.egg-info/top_level.txt