Metadata-Version: 2.1
Name: nlptoolkit-postagger-cy
Version: 1.0.5
Summary: English PosTagger Library
Home-page: https://github.com/StarlangSoftware/PosTagger-Cy
Author: olcaytaner
Author-email: olcay.yildiz@ozyegin.edu.tr
License: UNKNOWN
Platform: UNKNOWN
